brainfoose/__init__.py
brainfoose-2.0.3.dist-info/LICENSE.txt
brainfoose-2.0.3.dist-info/METADATA
brainfoose-2.0.3.dist-info/WHEEL
brainfoose-2.0.3.dist-info/entry_points.txt
brainfoose-2.0.3.dist-info/top_level.txt
brainfoose-2.0.3.dist-info/RECORD
