Metadata-Version: 2.1
Name: brainfoose
Version: 2.0.3
Summary: A brainfuck REPL.
Home-page: https://github.com/awesmubarak/brainfoose
Author: Awes Mubarak
Author-email: contact@awesmubarak.com
License: MIT
Keywords: brainfuck esoteric programming language repl
Platform: UNKNOWN
Classifier: Development Status :: 5 - Production/Stable
Classifier: Intended Audience :: Developers
Classifier: Topic :: Software Development
Classifier: Operating System :: OS Independent
Classifier: License :: OSI Approved :: MIT License
Classifier: Programming Language :: Python
Requires-Dist: docopt
Requires-Dist: termcolor
